taurex_ultranest/__init__.py
taurex_ultranest/ultranestoptimizer.py
taurex_ultranest-0.5.0a0.dist-info/LICENSE
taurex_ultranest-0.5.0a0.dist-info/METADATA
taurex_ultranest-0.5.0a0.dist-info/WHEEL
taurex_ultranest-0.5.0a0.dist-info/entry_points.txt
taurex_ultranest-0.5.0a0.dist-info/top_level.txt
taurex_ultranest-0.5.0a0.dist-info/RECORD
