Metadata-Version: 2.1
Name: taurex-ultranest
Version: 0.5.0a0
Summary: Ultranest plugin for TauREx-3 
Home-page: UNKNOWN
Author: Ahmed Faris Al-Refaie
Author-email: ahmed.al-refaie.12@ucl.ac.uk
License: BSD
Keywords: exoplanet,ultranest,sampling,nested sampling,taurex,chemistrytaurex,plugin,taurex3,atmosphere,atmospheric
Platform: UNKNOWN
Provides: taurex_ultranest
Requires-Dist: taurex
Requires-Dist: ultranest
